ibots/__init__.py
ibots/base.py
ibots/cli.py
ibots/client.py
ibots/ibots.py
ibots/server.py
ibots-0.1.4.dist-info/AUTHORS.rst
ibots-0.1.4.dist-info/LICENSE
ibots-0.1.4.dist-info/METADATA
ibots-0.1.4.dist-info/WHEEL
ibots-0.1.4.dist-info/entry_points.txt
ibots-0.1.4.dist-info/top_level.txt
ibots-0.1.4.dist-info/RECORD
