Metadata-Version: 2.1
Name: ibots
Version: 0.1.4
Summary: Token Ibis bot platform SDK
Home-page: https://github.com/TokenIbis/ibots
Author: Thien-Nam Dinh
Author-email: thiennam.tnd@gmail.com
License: MIT license
Keywords: ibots
Platform: UNKNOWN
Classifier: Development Status :: 2 - Pre-Alpha
Classifier: Intended Audience :: Developers
Classifier: License :: OSI Approved :: MIT License
Classifier: Natural Language :: English
Classifier: Programming Language :: Python :: 3
Classifier: Programming Language :: Python :: 3.5
Classifier: Programming Language :: Python :: 3.6
Classifier: Programming Language :: Python :: 3.7
Classifier: Programming Language :: Python :: 3.8
Requires-Python: >=3.5
Requires-Dist: flask
Requires-Dist: gql
Requires-Dist: ipython
